Metadata-Version: 2.1
Name: django-ru-validators
Version: 1.7.0
Summary: Django RU validators
Home-page: https://github.com/zhelyabuzhsky/django-ru-validators
Author: Ilya Zhelyabuzhsky
Author-email: zhelyabuzhsky@icloud.com
License: UNKNOWN
Platform: UNKNOWN
Classifier: Environment :: Web Environment
Classifier: Framework :: Django
Classifier: Framework :: Django :: 2.1
Classifier: Programming Language :: Python :: 3.7
Classifier: Operating System :: OS Independent
Requires-Python: >=3.7
